sgepy/SGE.py
sgepy/__init__.py
sgepy-0.1.2.data/scripts/sgepy-test.py
tests/__init__.py
tests/test_Dep.py
tests/test_Pool.py
tests/test_Worker.py
sgepy-0.1.2.dist-info/METADATA
sgepy-0.1.2.dist-info/WHEEL
sgepy-0.1.2.dist-info/top_level.txt
sgepy-0.1.2.dist-info/RECORD
